{"date": "2026-04-06", "markets": {"sp500": {"price": "6,582.69", "change": "+0.11%", "direction": "up", "sparkline": [6591.9, 6477.16, 6368.85, 6343.72, 6528.52, 6575.32, 6582.69]}, "nasdaq": {"price": "21,879.18", "change": "+0.18%", "direction": "up", "sparkline": [21929.82, 21408.08, 20948.36, 20794.64, 21590.63, 21840.95, 21879.18]}, "btc": {"price": "$69,934.38", "change": "+1.38%", "direction": "up", "sparkline": [68233.31, 68078.55, 66888.57, 66931.1, 67290.52, 68981.9, 69934.38]}, "eth": {"price": "$2,159.76", "change": "+2.36%", "direction": "up", "sparkline": [2104.71, 2138.74, 2056.85, 2053.39, 2065.35, 2109.0, 2159.76]}, "oil": {"price": "$107.30", "change": "-2.26%", "direction": "down", "sparkline": [112.78, 118.35, 101.16, 109.03, 107.3]}, "sentiment": {"value": "13", "label": "Extreme Fear", "direction": "down"}}}